{
  "schema_version": "4",
  "generated_at": "2026-05-09T22:19:39Z",
  "git_rev_short": "b48273c",
  "options": {
    "footballcsv_cache_fallback": true,
    "lookup_miss_sample_size": 200,
    "lookup_miss_seed": 42,
    "skip_lookup_miss_sample": false,
    "lookup_miss_classify_full_population": false,
    "lookup_miss_diagnostic_radius_days": 7
  },
  "meta_fingerprint_summary": {
    "feed_note": "manifest_wild=55_count=5",
    "augment_seed_count": 6716,
    "feeds_used_count": 5,
    "meta_index_size": 7112
  },
  "ids_total_manifest_events": 12141,
  "ids_in_join_scope": 6424,
  "ids_never_attempted_join": 5717,
  "supplement_counters": {
    "skipped_no_meta": 5425,
    "skipped_no_row": 982,
    "skipped_no_row_build_semantics": 982,
    "breakdown_in_scope": {
      "meta_no_valid_unix_attempted_lookup": 0,
      "lookup_miss_given_valid_unix": 982
    },
    "join_would_succeed_count": 17
  },
  "meta_state_per_event_aggregate": {
    "absent_key": 5425,
    "present_no_valid_unix": 0,
    "present_unix_ok": 6716
  },
  "kickoff_aggregate_global": {
    "absent_key": 5425,
    "present_no_valid_unix": 0,
    "present_unix_ok": 6716
  },
  "skipped_no_meta_by_dataset": {
    "bundesliga-2223": {
      "missing_meta": 103,
      "in_join_scope_events": 103,
      "share": 1.0
    },
    "bundesliga-2324": {
      "missing_meta": 104,
      "in_join_scope_events": 104,
      "share": 1.0
    },
    "bundesliga-2425": {
      "missing_meta": 104,
      "in_join_scope_events": 104,
      "share": 1.0
    },
    "bundesliga-2526": {
      "missing_meta": 149,
      "in_join_scope_events": 149,
      "share": 1.0
    },
    "carabao_cup-2223": {
      "missing_meta": 0,
      "in_join_scope_events": 93,
      "share": 0.0
    },
    "carabao_cup-2324": {
      "missing_meta": 0,
      "in_join_scope_events": 93,
      "share": 0.0
    },
    "carabao_cup-2425": {
      "missing_meta": 0,
      "in_join_scope_events": 93,
      "share": 0.0
    },
    "carabao_cup-2526": {
      "missing_meta": 0,
      "in_join_scope_events": 93,
      "share": 0.0
    },
    "chance_liga-2223": {
      "missing_meta": 107,
      "in_join_scope_events": 107,
      "share": 1.0
    },
    "chance_liga-2324": {
      "missing_meta": 108,
      "in_join_scope_events": 108,
      "share": 1.0
    },
    "chance_liga-2425": {
      "missing_meta": 105,
      "in_join_scope_events": 105,
      "share": 1.0
    },
    "chance_liga-2526": {
      "missing_meta": 124,
      "in_join_scope_events": 124,
      "share": 1.0
    },
    "ekstraklasa-2223": {
      "missing_meta": 104,
      "in_join_scope_events": 104,
      "share": 1.0
    },
    "ekstraklasa-2324": {
      "missing_meta": 105,
      "in_join_scope_events": 105,
      "share": 1.0
    },
    "ekstraklasa-2425": {
      "missing_meta": 106,
      "in_join_scope_events": 106,
      "share": 1.0
    },
    "ekstraklasa-2526": {
      "missing_meta": 0,
      "in_join_scope_events": 159,
      "share": 0.0
    },
    "eredivisie-2223": {
      "missing_meta": 108,
      "in_join_scope_events": 108,
      "share": 1.0
    },
    "eredivisie-2324": {
      "missing_meta": 104,
      "in_join_scope_events": 104,
      "share": 1.0
    },
    "eredivisie-2425": {
      "missing_meta": 104,
      "in_join_scope_events": 104,
      "share": 1.0
    },
    "eredivisie-2526": {
      "missing_meta": 136,
      "in_join_scope_events": 136,
      "share": 1.0
    },
    "fa_cup-2223": {
      "missing_meta": 0,
      "in_join_scope_events": 106,
      "share": 0.0
    },
    "fa_cup-2324": {
      "missing_meta": 0,
      "in_join_scope_events": 109,
      "share": 0.0
    },
    "fa_cup-2425": {
      "missing_meta": 0,
      "in_join_scope_events": 123,
      "share": 0.0
    },
    "fa_cup-2526": {
      "missing_meta": 0,
      "in_join_scope_events": 130,
      "share": 0.0
    },
    "jupiler_league-2223": {
      "missing_meta": 109,
      "in_join_scope_events": 109,
      "share": 1.0
    },
    "jupiler_league-2324": {
      "missing_meta": 104,
      "in_join_scope_events": 104,
      "share": 1.0
    },
    "jupiler_league-2425": {
      "missing_meta": 109,
      "in_join_scope_events": 109,
      "share": 1.0
    },
    "jupiler_league-2526": {
      "missing_meta": 141,
      "in_join_scope_events": 141,
      "share": 1.0
    },
    "laliga-2223": {
      "missing_meta": 105,
      "in_join_scope_events": 105,
      "share": 1.0
    },
    "laliga-2324": {
      "missing_meta": 106,
      "in_join_scope_events": 106,
      "share": 1.0
    },
    "laliga-2425": {
      "missing_meta": 107,
      "in_join_scope_events": 107,
      "share": 1.0
    },
    "laliga-2526": {
      "missing_meta": 176,
      "in_join_scope_events": 176,
      "share": 1.0
    },
    "liga_portugal-2223": {
      "missing_meta": 105,
      "in_join_scope_events": 105,
      "share": 1.0
    },
    "liga_portugal-2324": {
      "missing_meta": 103,
      "in_join_scope_events": 103,
      "share": 1.0
    },
    "liga_portugal-2425": {
      "missing_meta": 106,
      "in_join_scope_events": 106,
      "share": 1.0
    },
    "liga_portugal-2526": {
      "missing_meta": 154,
      "in_join_scope_events": 154,
      "share": 1.0
    },
    "ligue_1-2223": {
      "missing_meta": 109,
      "in_join_scope_events": 109,
      "share": 1.0
    },
    "ligue_1-2324": {
      "missing_meta": 109,
      "in_join_scope_events": 109,
      "share": 1.0
    },
    "ligue_1-2425": {
      "missing_meta": 108,
      "in_join_scope_events": 108,
      "share": 1.0
    },
    "ligue_1-2526": {
      "missing_meta": 134,
      "in_join_scope_events": 134,
      "share": 1.0
    },
    "premier_league-2223": {
      "missing_meta": 103,
      "in_join_scope_events": 103,
      "share": 1.0
    },
    "premier_league-2324": {
      "missing_meta": 103,
      "in_join_scope_events": 103,
      "share": 1.0
    },
    "premier_league-2425": {
      "missing_meta": 109,
      "in_join_scope_events": 109,
      "share": 1.0
    },
    "premier_league-2526": {
      "missing_meta": 168,
      "in_join_scope_events": 168,
      "share": 1.0
    },
    "serie_a-2223": {
      "missing_meta": 103,
      "in_join_scope_events": 103,
      "share": 1.0
    },
    "serie_a-2324": {
      "missing_meta": 105,
      "in_join_scope_events": 105,
      "share": 1.0
    },
    "serie_a-2425": {
      "missing_meta": 105,
      "in_join_scope_events": 105,
      "share": 1.0
    },
    "serie_a-2526": {
      "missing_meta": 168,
      "in_join_scope_events": 168,
      "share": 1.0
    },
    "super_league-2223": {
      "missing_meta": 105,
      "in_join_scope_events": 105,
      "share": 1.0
    },
    "super_league-2324": {
      "missing_meta": 107,
      "in_join_scope_events": 107,
      "share": 1.0
    },
    "super_league-2425": {
      "missing_meta": 104,
      "in_join_scope_events": 104,
      "share": 1.0
    },
    "super_league-2526": {
      "missing_meta": 136,
      "in_join_scope_events": 136,
      "share": 1.0
    },
    "super_lig-2223": {
      "missing_meta": 108,
      "in_join_scope_events": 108,
      "share": 1.0
    },
    "super_lig-2324": {
      "missing_meta": 106,
      "in_join_scope_events": 106,
      "share": 1.0
    },
    "super_lig-2425": {
      "missing_meta": 107,
      "in_join_scope_events": 107,
      "share": 1.0
    },
    "super_lig-2526": {
      "missing_meta": 132,
      "in_join_scope_events": 132,
      "share": 1.0
    }
  },
  "kickoff_histogram_by_dataset": {
    "bundesliga-2223": {
      "absent_key": 103,
      "present_no_valid_unix": 0,
      "present_unix_ok": 0
    },
    "bundesliga-2324": {
      "absent_key": 104,
      "present_no_valid_unix": 0,
      "present_unix_ok": 0
    },
    "bundesliga-2425": {
      "absent_key": 104,
      "present_no_valid_unix": 0,
      "present_unix_ok": 0
    },
    "bundesliga-2526": {
      "absent_key": 149,
      "present_no_valid_unix": 0,
      "present_unix_ok": 0
    },
    "carabao_cup-2223": {
      "absent_key": 0,
      "present_no_valid_unix": 0,
      "present_unix_ok": 93
    },
    "carabao_cup-2324": {
      "absent_key": 0,
      "present_no_valid_unix": 0,
      "present_unix_ok": 93
    },
    "carabao_cup-2425": {
      "absent_key": 0,
      "present_no_valid_unix": 0,
      "present_unix_ok": 93
    },
    "carabao_cup-2526": {
      "absent_key": 0,
      "present_no_valid_unix": 0,
      "present_unix_ok": 93
    },
    "chance_liga-2223": {
      "absent_key": 107,
      "present_no_valid_unix": 0,
      "present_unix_ok": 0
    },
    "chance_liga-2324": {
      "absent_key": 108,
      "present_no_valid_unix": 0,
      "present_unix_ok": 0
    },
    "chance_liga-2425": {
      "absent_key": 105,
      "present_no_valid_unix": 0,
      "present_unix_ok": 0
    },
    "chance_liga-2526": {
      "absent_key": 124,
      "present_no_valid_unix": 0,
      "present_unix_ok": 0
    },
    "copa_del_rey-2223": {
      "absent_key": 0,
      "present_no_valid_unix": 0,
      "present_unix_ok": 126
    },
    "copa_del_rey-2324": {
      "absent_key": 0,
      "present_no_valid_unix": 0,
      "present_unix_ok": 116
    },
    "copa_del_rey-2425": {
      "absent_key": 0,
      "present_no_valid_unix": 0,
      "present_unix_ok": 116
    },
    "copa_del_rey-2526": {
      "absent_key": 0,
      "present_no_valid_unix": 0,
      "present_unix_ok": 127
    },
    "coppa_italia-2223": {
      "absent_key": 0,
      "present_no_valid_unix": 0,
      "present_unix_ok": 45
    },
    "coppa_italia-2324": {
      "absent_key": 0,
      "present_no_valid_unix": 0,
      "present_unix_ok": 45
    },
    "coppa_italia-2425": {
      "absent_key": 0,
      "present_no_valid_unix": 0,
      "present_unix_ok": 45
    },
    "coppa_italia-2526": {
      "absent_key": 0,
      "present_no_valid_unix": 0,
      "present_unix_ok": 45
    },
    "coupe_de_france-2223": {
      "absent_key": 0,
      "present_no_valid_unix": 0,
      "present_unix_ok": 107
    },
    "coupe_de_france-2324": {
      "absent_key": 0,
      "present_no_valid_unix": 0,
      "present_unix_ok": 111
    },
    "coupe_de_france-2425": {
      "absent_key": 0,
      "present_no_valid_unix": 0,
      "present_unix_ok": 108
    },
    "coupe_de_france-2526": {
      "absent_key": 0,
      "present_no_valid_unix": 0,
      "present_unix_ok": 109
    },
    "dfb_pokal-2223": {
      "absent_key": 0,
      "present_no_valid_unix": 0,
      "present_unix_ok": 63
    },
    "dfb_pokal-2324": {
      "absent_key": 0,
      "present_no_valid_unix": 0,
      "present_unix_ok": 63
    },
    "dfb_pokal-2425": {
      "absent_key": 0,
      "present_no_valid_unix": 0,
      "present_unix_ok": 63
    },
    "dfb_pokal-2526": {
      "absent_key": 0,
      "present_no_valid_unix": 0,
      "present_unix_ok": 63
    },
    "ekstraklasa-2223": {
      "absent_key": 104,
      "present_no_valid_unix": 0,
      "present_unix_ok": 0
    },
    "ekstraklasa-2324": {
      "absent_key": 105,
      "present_no_valid_unix": 0,
      "present_unix_ok": 0
    },
    "ekstraklasa-2425": {
      "absent_key": 106,
      "present_no_valid_unix": 0,
      "present_unix_ok": 0
    },
    "ekstraklasa-2526": {
      "absent_key": 0,
      "present_no_valid_unix": 0,
      "present_unix_ok": 159
    },
    "eredivisie-2223": {
      "absent_key": 108,
      "present_no_valid_unix": 0,
      "present_unix_ok": 0
    },
    "eredivisie-2324": {
      "absent_key": 104,
      "present_no_valid_unix": 0,
      "present_unix_ok": 0
    },
    "eredivisie-2425": {
      "absent_key": 104,
      "present_no_valid_unix": 0,
      "present_unix_ok": 0
    },
    "eredivisie-2526": {
      "absent_key": 136,
      "present_no_valid_unix": 0,
      "present_unix_ok": 0
    },
    "fa_cup-2223": {
      "absent_key": 0,
      "present_no_valid_unix": 0,
      "present_unix_ok": 106
    },
    "fa_cup-2324": {
      "absent_key": 0,
      "present_no_valid_unix": 0,
      "present_unix_ok": 109
    },
    "fa_cup-2425": {
      "absent_key": 0,
      "present_no_valid_unix": 0,
      "present_unix_ok": 123
    },
    "fa_cup-2526": {
      "absent_key": 0,
      "present_no_valid_unix": 0,
      "present_unix_ok": 130
    },
    "jupiler_league-2223": {
      "absent_key": 109,
      "present_no_valid_unix": 0,
      "present_unix_ok": 0
    },
    "jupiler_league-2324": {
      "absent_key": 104,
      "present_no_valid_unix": 0,
      "present_unix_ok": 0
    },
    "jupiler_league-2425": {
      "absent_key": 109,
      "present_no_valid_unix": 0,
      "present_unix_ok": 0
    },
    "jupiler_league-2526": {
      "absent_key": 141,
      "present_no_valid_unix": 0,
      "present_unix_ok": 0
    },
    "knvb_beker-2223": {
      "absent_key": 0,
      "present_no_valid_unix": 0,
      "present_unix_ok": 85
    },
    "knvb_beker-2324": {
      "absent_key": 0,
      "present_no_valid_unix": 0,
      "present_unix_ok": 109
    },
    "knvb_beker-2425": {
      "absent_key": 0,
      "present_no_valid_unix": 0,
      "present_unix_ok": 109
    },
    "knvb_beker-2526": {
      "absent_key": 0,
      "present_no_valid_unix": 0,
      "present_unix_ok": 109
    },
    "laliga-2223": {
      "absent_key": 105,
      "present_no_valid_unix": 0,
      "present_unix_ok": 0
    },
    "laliga-2324": {
      "absent_key": 106,
      "present_no_valid_unix": 0,
      "present_unix_ok": 0
    },
    "laliga-2425": {
      "absent_key": 107,
      "present_no_valid_unix": 0,
      "present_unix_ok": 0
    },
    "laliga-2526": {
      "absent_key": 176,
      "present_no_valid_unix": 0,
      "present_unix_ok": 0
    },
    "liga_europy-2223": {
      "absent_key": 0,
      "present_no_valid_unix": 0,
      "present_unix_ok": 125
    },
    "liga_europy-2324": {
      "absent_key": 0,
      "present_no_valid_unix": 0,
      "present_unix_ok": 125
    },
    "liga_europy-2425": {
      "absent_key": 0,
      "present_no_valid_unix": 0,
      "present_unix_ok": 134
    },
    "liga_europy-2526": {
      "absent_key": 0,
      "present_no_valid_unix": 0,
      "present_unix_ok": 134
    },
    "liga_konferencji-2223": {
      "absent_key": 0,
      "present_no_valid_unix": 0,
      "present_unix_ok": 125
    },
    "liga_konferencji-2324": {
      "absent_key": 0,
      "present_no_valid_unix": 0,
      "present_unix_ok": 125
    },
    "liga_konferencji-2425": {
      "absent_key": 0,
      "present_no_valid_unix": 0,
      "present_unix_ok": 135
    },
    "liga_konferencji-2526": {
      "absent_key": 0,
      "present_no_valid_unix": 0,
      "present_unix_ok": 134
    },
    "liga_mistrzow-2223": {
      "absent_key": 0,
      "present_no_valid_unix": 0,
      "present_unix_ok": 109
    },
    "liga_mistrzow-2324": {
      "absent_key": 0,
      "present_no_valid_unix": 0,
      "present_unix_ok": 109
    },
    "liga_mistrzow-2425": {
      "absent_key": 0,
      "present_no_valid_unix": 0,
      "present_unix_ok": 117
    },
    "liga_mistrzow-2526": {
      "absent_key": 0,
      "present_no_valid_unix": 0,
      "present_unix_ok": 116
    },
    "liga_portugal-2223": {
      "absent_key": 105,
      "present_no_valid_unix": 0,
      "present_unix_ok": 0
    },
    "liga_portugal-2324": {
      "absent_key": 103,
      "present_no_valid_unix": 0,
      "present_unix_ok": 0
    },
    "liga_portugal-2425": {
      "absent_key": 106,
      "present_no_valid_unix": 0,
      "present_unix_ok": 0
    },
    "liga_portugal-2526": {
      "absent_key": 154,
      "present_no_valid_unix": 0,
      "present_unix_ok": 0
    },
    "ligue_1-2223": {
      "absent_key": 109,
      "present_no_valid_unix": 0,
      "present_unix_ok": 0
    },
    "ligue_1-2324": {
      "absent_key": 109,
      "present_no_valid_unix": 0,
      "present_unix_ok": 0
    },
    "ligue_1-2425": {
      "absent_key": 108,
      "present_no_valid_unix": 0,
      "present_unix_ok": 0
    },
    "ligue_1-2526": {
      "absent_key": 134,
      "present_no_valid_unix": 0,
      "present_unix_ok": 0
    },
    "premier_league-2223": {
      "absent_key": 103,
      "present_no_valid_unix": 0,
      "present_unix_ok": 0
    },
    "premier_league-2324": {
      "absent_key": 103,
      "present_no_valid_unix": 0,
      "present_unix_ok": 0
    },
    "premier_league-2425": {
      "absent_key": 109,
      "present_no_valid_unix": 0,
      "present_unix_ok": 0
    },
    "premier_league-2526": {
      "absent_key": 168,
      "present_no_valid_unix": 0,
      "present_unix_ok": 0
    },
    "puchar_belgii-2223": {
      "absent_key": 0,
      "present_no_valid_unix": 0,
      "present_unix_ok": 121
    },
    "puchar_belgii-2324": {
      "absent_key": 0,
      "present_no_valid_unix": 0,
      "present_unix_ok": 109
    },
    "puchar_belgii-2425": {
      "absent_key": 0,
      "present_no_valid_unix": 0,
      "present_unix_ok": 153
    },
    "puchar_belgii-2526": {
      "absent_key": 0,
      "present_no_valid_unix": 0,
      "present_unix_ok": 33
    },
    "puchar_czech-2223": {
      "absent_key": 0,
      "present_no_valid_unix": 0,
      "present_unix_ok": 103
    },
    "puchar_czech-2324": {
      "absent_key": 0,
      "present_no_valid_unix": 0,
      "present_unix_ok": 116
    },
    "puchar_czech-2425": {
      "absent_key": 0,
      "present_no_valid_unix": 0,
      "present_unix_ok": 104
    },
    "puchar_czech-2526": {
      "absent_key": 0,
      "present_no_valid_unix": 0,
      "present_unix_ok": 124
    },
    "puchar_grecji-2223": {
      "absent_key": 0,
      "present_no_valid_unix": 0,
      "present_unix_ok": 97
    },
    "puchar_grecji-2324": {
      "absent_key": 0,
      "present_no_valid_unix": 0,
      "present_unix_ok": 92
    },
    "puchar_grecji-2425": {
      "absent_key": 0,
      "present_no_valid_unix": 0,
      "present_unix_ok": 93
    },
    "puchar_grecji-2526": {
      "absent_key": 0,
      "present_no_valid_unix": 0,
      "present_unix_ok": 64
    },
    "puchar_polski-2223": {
      "absent_key": 0,
      "present_no_valid_unix": 0,
      "present_unix_ok": 69
    },
    "puchar_polski-2324": {
      "absent_key": 0,
      "present_no_valid_unix": 0,
      "present_unix_ok": 69
    },
    "puchar_polski-2425": {
      "absent_key": 0,
      "present_no_valid_unix": 0,
      "present_unix_ok": 69
    },
    "puchar_polski-2526": {
      "absent_key": 0,
      "present_no_valid_unix": 0,
      "present_unix_ok": 69
    },
    "puchar_turcji-2223": {
      "absent_key": 0,
      "present_no_valid_unix": 0,
      "present_unix_ok": 123
    },
    "puchar_turcji-2324": {
      "absent_key": 0,
      "present_no_valid_unix": 0,
      "present_unix_ok": 120
    },
    "puchar_turcji-2425": {
      "absent_key": 0,
      "present_no_valid_unix": 0,
      "present_unix_ok": 126
    },
    "puchar_turcji-2526": {
      "absent_key": 0,
      "present_no_valid_unix": 0,
      "present_unix_ok": 130
    },
    "serie_a-2223": {
      "absent_key": 103,
      "present_no_valid_unix": 0,
      "present_unix_ok": 0
    },
    "serie_a-2324": {
      "absent_key": 105,
      "present_no_valid_unix": 0,
      "present_unix_ok": 0
    },
    "serie_a-2425": {
      "absent_key": 105,
      "present_no_valid_unix": 0,
      "present_unix_ok": 0
    },
    "serie_a-2526": {
      "absent_key": 168,
      "present_no_valid_unix": 0,
      "present_unix_ok": 0
    },
    "super_league-2223": {
      "absent_key": 105,
      "present_no_valid_unix": 0,
      "present_unix_ok": 0
    },
    "super_league-2324": {
      "absent_key": 107,
      "present_no_valid_unix": 0,
      "present_unix_ok": 0
    },
    "super_league-2425": {
      "absent_key": 104,
      "present_no_valid_unix": 0,
      "present_unix_ok": 0
    },
    "super_league-2526": {
      "absent_key": 136,
      "present_no_valid_unix": 0,
      "present_unix_ok": 0
    },
    "super_lig-2223": {
      "absent_key": 108,
      "present_no_valid_unix": 0,
      "present_unix_ok": 0
    },
    "super_lig-2324": {
      "absent_key": 106,
      "present_no_valid_unix": 0,
      "present_unix_ok": 0
    },
    "super_lig-2425": {
      "absent_key": 107,
      "present_no_valid_unix": 0,
      "present_unix_ok": 0
    },
    "super_lig-2526": {
      "absent_key": 132,
      "present_no_valid_unix": 0,
      "present_unix_ok": 0
    },
    "taca_de_portugal-2223": {
      "absent_key": 0,
      "present_no_valid_unix": 0,
      "present_unix_ok": 148
    },
    "taca_de_portugal-2324": {
      "absent_key": 0,
      "present_no_valid_unix": 0,
      "present_unix_ok": 111
    },
    "taca_de_portugal-2425": {
      "absent_key": 0,
      "present_no_valid_unix": 0,
      "present_unix_ok": 110
    },
    "taca_de_portugal-2526": {
      "absent_key": 0,
      "present_no_valid_unix": 0,
      "present_unix_ok": 112
    }
  },
  "league_join_scope_table": [
    {
      "dataset_label": "ekstraklasa-2223",
      "ids_name": "ekstraklasa_2223",
      "ids_file": "present",
      "ids_event_count": 104,
      "join_scope": "ekstraklasa_pol_agg",
      "join_detail": null,
      "cli": "POL_AGG",
      "division": null
    },
    {
      "dataset_label": "ekstraklasa-2324",
      "ids_name": "ekstraklasa_2324",
      "ids_file": "present",
      "ids_event_count": 105,
      "join_scope": "ekstraklasa_pol_agg",
      "join_detail": null,
      "cli": "POL_AGG",
      "division": null
    },
    {
      "dataset_label": "ekstraklasa-2425",
      "ids_name": "ekstraklasa_2425",
      "ids_file": "present",
      "ids_event_count": 106,
      "join_scope": "ekstraklasa_pol_agg",
      "join_detail": null,
      "cli": "POL_AGG",
      "division": null
    },
    {
      "dataset_label": "ekstraklasa-2526",
      "ids_name": "ekstraklasa_2526",
      "ids_file": "present",
      "ids_event_count": 159,
      "join_scope": "ekstraklasa_pol_agg",
      "join_detail": null,
      "cli": "POL_AGG",
      "division": null
    },
    {
      "dataset_label": "chance_liga-2223",
      "ids_name": "chance_liga_2223",
      "ids_file": "present",
      "ids_event_count": 107,
      "join_scope": "leag_key_to_cli",
      "join_detail": "mmz",
      "cli": "CZE1",
      "division": "C1"
    },
    {
      "dataset_label": "chance_liga-2324",
      "ids_name": "chance_liga_2324",
      "ids_file": "present",
      "ids_event_count": 108,
      "join_scope": "leag_key_to_cli",
      "join_detail": "mmz",
      "cli": "CZE1",
      "division": "C1"
    },
    {
      "dataset_label": "chance_liga-2425",
      "ids_name": "chance_liga_2425",
      "ids_file": "present",
      "ids_event_count": 105,
      "join_scope": "leag_key_to_cli",
      "join_detail": "mmz",
      "cli": "CZE1",
      "division": "C1"
    },
    {
      "dataset_label": "chance_liga-2526",
      "ids_name": "chance_liga_2526",
      "ids_file": "present",
      "ids_event_count": 124,
      "join_scope": "leag_key_to_cli",
      "join_detail": "mmz",
      "cli": "CZE1",
      "division": "C1"
    },
    {
      "dataset_label": "liga_portugal-2223",
      "ids_name": "liga_portugal_2223",
      "ids_file": "present",
      "ids_event_count": 105,
      "join_scope": "leag_key_to_cli",
      "join_detail": "mmz",
      "cli": "POR1",
      "division": "P1"
    },
    {
      "dataset_label": "liga_portugal-2324",
      "ids_name": "liga_portugal_2324",
      "ids_file": "present",
      "ids_event_count": 103,
      "join_scope": "leag_key_to_cli",
      "join_detail": "mmz",
      "cli": "POR1",
      "division": "P1"
    },
    {
      "dataset_label": "liga_portugal-2425",
      "ids_name": "liga_portugal_2425",
      "ids_file": "present",
      "ids_event_count": 106,
      "join_scope": "leag_key_to_cli",
      "join_detail": "mmz",
      "cli": "POR1",
      "division": "P1"
    },
    {
      "dataset_label": "liga_portugal-2526",
      "ids_name": "liga_portugal_2526",
      "ids_file": "present",
      "ids_event_count": 154,
      "join_scope": "leag_key_to_cli",
      "join_detail": "mmz",
      "cli": "POR1",
      "division": "P1"
    },
    {
      "dataset_label": "laliga-2223",
      "ids_name": "laliga_2223",
      "ids_file": "present",
      "ids_event_count": 105,
      "join_scope": "leag_key_to_cli",
      "join_detail": "mmz",
      "cli": "ESP1",
      "division": "SP1"
    },
    {
      "dataset_label": "laliga-2324",
      "ids_name": "laliga_2324",
      "ids_file": "present",
      "ids_event_count": 106,
      "join_scope": "leag_key_to_cli",
      "join_detail": "mmz",
      "cli": "ESP1",
      "division": "SP1"
    },
    {
      "dataset_label": "laliga-2425",
      "ids_name": "laliga_2425",
      "ids_file": "present",
      "ids_event_count": 107,
      "join_scope": "leag_key_to_cli",
      "join_detail": "mmz",
      "cli": "ESP1",
      "division": "SP1"
    },
    {
      "dataset_label": "laliga-2526",
      "ids_name": "laliga_2526",
      "ids_file": "present",
      "ids_event_count": 176,
      "join_scope": "leag_key_to_cli",
      "join_detail": "mmz",
      "cli": "ESP1",
      "division": "SP1"
    },
    {
      "dataset_label": "serie_a-2223",
      "ids_name": "serie_a_2223",
      "ids_file": "present",
      "ids_event_count": 103,
      "join_scope": "leag_key_to_cli",
      "join_detail": "mmz",
      "cli": "ITA1",
      "division": "I1"
    },
    {
      "dataset_label": "serie_a-2324",
      "ids_name": "serie_a_2324",
      "ids_file": "present",
      "ids_event_count": 105,
      "join_scope": "leag_key_to_cli",
      "join_detail": "mmz",
      "cli": "ITA1",
      "division": "I1"
    },
    {
      "dataset_label": "serie_a-2425",
      "ids_name": "serie_a_2425",
      "ids_file": "present",
      "ids_event_count": 105,
      "join_scope": "leag_key_to_cli",
      "join_detail": "mmz",
      "cli": "ITA1",
      "division": "I1"
    },
    {
      "dataset_label": "serie_a-2526",
      "ids_name": "serie_a_2526",
      "ids_file": "present",
      "ids_event_count": 168,
      "join_scope": "leag_key_to_cli",
      "join_detail": "mmz",
      "cli": "ITA1",
      "division": "I1"
    },
    {
      "dataset_label": "premier_league-2223",
      "ids_name": "premier_league_2223",
      "ids_file": "present",
      "ids_event_count": 103,
      "join_scope": "leag_key_to_cli",
      "join_detail": "mmz",
      "cli": "ENG1",
      "division": "E0"
    },
    {
      "dataset_label": "premier_league-2324",
      "ids_name": "premier_league_2324",
      "ids_file": "present",
      "ids_event_count": 103,
      "join_scope": "leag_key_to_cli",
      "join_detail": "mmz",
      "cli": "ENG1",
      "division": "E0"
    },
    {
      "dataset_label": "premier_league-2425",
      "ids_name": "premier_league_2425",
      "ids_file": "present",
      "ids_event_count": 109,
      "join_scope": "leag_key_to_cli",
      "join_detail": "mmz",
      "cli": "ENG1",
      "division": "E0"
    },
    {
      "dataset_label": "premier_league-2526",
      "ids_name": "premier_league_2526",
      "ids_file": "present",
      "ids_event_count": 168,
      "join_scope": "leag_key_to_cli",
      "join_detail": "mmz",
      "cli": "ENG1",
      "division": "E0"
    },
    {
      "dataset_label": "bundesliga-2223",
      "ids_name": "bundesliga_2223",
      "ids_file": "present",
      "ids_event_count": 103,
      "join_scope": "leag_key_to_cli",
      "join_detail": "mmz",
      "cli": "GER1",
      "division": "D1"
    },
    {
      "dataset_label": "bundesliga-2324",
      "ids_name": "bundesliga_2324",
      "ids_file": "present",
      "ids_event_count": 104,
      "join_scope": "leag_key_to_cli",
      "join_detail": "mmz",
      "cli": "GER1",
      "division": "D1"
    },
    {
      "dataset_label": "bundesliga-2425",
      "ids_name": "bundesliga_2425",
      "ids_file": "present",
      "ids_event_count": 104,
      "join_scope": "leag_key_to_cli",
      "join_detail": "mmz",
      "cli": "GER1",
      "division": "D1"
    },
    {
      "dataset_label": "bundesliga-2526",
      "ids_name": "bundesliga_2526",
      "ids_file": "present",
      "ids_event_count": 149,
      "join_scope": "leag_key_to_cli",
      "join_detail": "mmz",
      "cli": "GER1",
      "division": "D1"
    },
    {
      "dataset_label": "ligue_1-2223",
      "ids_name": "ligue_1_2223",
      "ids_file": "present",
      "ids_event_count": 109,
      "join_scope": "leag_key_to_cli",
      "join_detail": "mmz",
      "cli": "FRA1",
      "division": "F1"
    },
    {
      "dataset_label": "ligue_1-2324",
      "ids_name": "ligue_1_2324",
      "ids_file": "present",
      "ids_event_count": 109,
      "join_scope": "leag_key_to_cli",
      "join_detail": "mmz",
      "cli": "FRA1",
      "division": "F1"
    },
    {
      "dataset_label": "ligue_1-2425",
      "ids_name": "ligue_1_2425",
      "ids_file": "present",
      "ids_event_count": 108,
      "join_scope": "leag_key_to_cli",
      "join_detail": "mmz",
      "cli": "FRA1",
      "division": "F1"
    },
    {
      "dataset_label": "ligue_1-2526",
      "ids_name": "ligue_1_2526",
      "ids_file": "present",
      "ids_event_count": 134,
      "join_scope": "leag_key_to_cli",
      "join_detail": "mmz",
      "cli": "FRA1",
      "division": "F1"
    },
    {
      "dataset_label": "eredivisie-2223",
      "ids_name": "eredivisie_2223",
      "ids_file": "present",
      "ids_event_count": 108,
      "join_scope": "leag_key_to_cli",
      "join_detail": "mmz",
      "cli": "NED1",
      "division": "N1"
    },
    {
      "dataset_label": "eredivisie-2324",
      "ids_name": "eredivisie_2324",
      "ids_file": "present",
      "ids_event_count": 104,
      "join_scope": "leag_key_to_cli",
      "join_detail": "mmz",
      "cli": "NED1",
      "division": "N1"
    },
    {
      "dataset_label": "eredivisie-2425",
      "ids_name": "eredivisie_2425",
      "ids_file": "present",
      "ids_event_count": 104,
      "join_scope": "leag_key_to_cli",
      "join_detail": "mmz",
      "cli": "NED1",
      "division": "N1"
    },
    {
      "dataset_label": "eredivisie-2526",
      "ids_name": "eredivisie_2526",
      "ids_file": "present",
      "ids_event_count": 136,
      "join_scope": "leag_key_to_cli",
      "join_detail": "mmz",
      "cli": "NED1",
      "division": "N1"
    },
    {
      "dataset_label": "jupiler_league-2223",
      "ids_name": "jupiler_league_2223",
      "ids_file": "present",
      "ids_event_count": 109,
      "join_scope": "leag_key_to_cli",
      "join_detail": "mmz",
      "cli": "BEL1",
      "division": "B1"
    },
    {
      "dataset_label": "jupiler_league-2324",
      "ids_name": "jupiler_league_2324",
      "ids_file": "present",
      "ids_event_count": 104,
      "join_scope": "leag_key_to_cli",
      "join_detail": "mmz",
      "cli": "BEL1",
      "division": "B1"
    },
    {
      "dataset_label": "jupiler_league-2425",
      "ids_name": "jupiler_league_2425",
      "ids_file": "present",
      "ids_event_count": 109,
      "join_scope": "leag_key_to_cli",
      "join_detail": "mmz",
      "cli": "BEL1",
      "division": "B1"
    },
    {
      "dataset_label": "jupiler_league-2526",
      "ids_name": "jupiler_league_2526",
      "ids_file": "present",
      "ids_event_count": 141,
      "join_scope": "leag_key_to_cli",
      "join_detail": "mmz",
      "cli": "BEL1",
      "division": "B1"
    },
    {
      "dataset_label": "super_league-2223",
      "ids_name": "super_league_2223",
      "ids_file": "present",
      "ids_event_count": 105,
      "join_scope": "leag_key_to_cli",
      "join_detail": "mmz",
      "cli": "GRE1",
      "division": "G1"
    },
    {
      "dataset_label": "super_league-2324",
      "ids_name": "super_league_2324",
      "ids_file": "present",
      "ids_event_count": 107,
      "join_scope": "leag_key_to_cli",
      "join_detail": "mmz",
      "cli": "GRE1",
      "division": "G1"
    },
    {
      "dataset_label": "super_league-2425",
      "ids_name": "super_league_2425",
      "ids_file": "present",
      "ids_event_count": 104,
      "join_scope": "leag_key_to_cli",
      "join_detail": "mmz",
      "cli": "GRE1",
      "division": "G1"
    },
    {
      "dataset_label": "super_league-2526",
      "ids_name": "super_league_2526",
      "ids_file": "present",
      "ids_event_count": 136,
      "join_scope": "leag_key_to_cli",
      "join_detail": "mmz",
      "cli": "GRE1",
      "division": "G1"
    },
    {
      "dataset_label": "super_lig-2223",
      "ids_name": "super_lig_2223",
      "ids_file": "present",
      "ids_event_count": 108,
      "join_scope": "leag_key_to_cli",
      "join_detail": "mmz",
      "cli": "TUR1",
      "division": "T1"
    },
    {
      "dataset_label": "super_lig-2324",
      "ids_name": "super_lig_2324",
      "ids_file": "present",
      "ids_event_count": 106,
      "join_scope": "leag_key_to_cli",
      "join_detail": "mmz",
      "cli": "TUR1",
      "division": "T1"
    },
    {
      "dataset_label": "super_lig-2425",
      "ids_name": "super_lig_2425",
      "ids_file": "present",
      "ids_event_count": 107,
      "join_scope": "leag_key_to_cli",
      "join_detail": "mmz",
      "cli": "TUR1",
      "division": "T1"
    },
    {
      "dataset_label": "super_lig-2526",
      "ids_name": "super_lig_2526",
      "ids_file": "present",
      "ids_event_count": 132,
      "join_scope": "leag_key_to_cli",
      "join_detail": "mmz",
      "cli": "TUR1",
      "division": "T1"
    },
    {
      "dataset_label": "liga_mistrzow-2223",
      "ids_name": "liga_mistrzow_2223",
      "ids_file": "present",
      "ids_event_count": 109,
      "join_scope": "unsupported_league_key",
      "join_detail": "liga_mistrzow"
    },
    {
      "dataset_label": "liga_mistrzow-2324",
      "ids_name": "liga_mistrzow_2324",
      "ids_file": "present",
      "ids_event_count": 109,
      "join_scope": "unsupported_league_key",
      "join_detail": "liga_mistrzow"
    },
    {
      "dataset_label": "liga_mistrzow-2425",
      "ids_name": "liga_mistrzow_2425",
      "ids_file": "present",
      "ids_event_count": 117,
      "join_scope": "unsupported_league_key",
      "join_detail": "liga_mistrzow"
    },
    {
      "dataset_label": "liga_mistrzow-2526",
      "ids_name": "liga_mistrzow_2526",
      "ids_file": "present",
      "ids_event_count": 116,
      "join_scope": "unsupported_league_key",
      "join_detail": "liga_mistrzow"
    },
    {
      "dataset_label": "liga_europy-2223",
      "ids_name": "liga_europy_2223",
      "ids_file": "present",
      "ids_event_count": 125,
      "join_scope": "unsupported_league_key",
      "join_detail": "liga_europy"
    },
    {
      "dataset_label": "liga_europy-2324",
      "ids_name": "liga_europy_2324",
      "ids_file": "present",
      "ids_event_count": 125,
      "join_scope": "unsupported_league_key",
      "join_detail": "liga_europy"
    },
    {
      "dataset_label": "liga_europy-2425",
      "ids_name": "liga_europy_2425",
      "ids_file": "present",
      "ids_event_count": 134,
      "join_scope": "unsupported_league_key",
      "join_detail": "liga_europy"
    },
    {
      "dataset_label": "liga_europy-2526",
      "ids_name": "liga_europy_2526",
      "ids_file": "present",
      "ids_event_count": 134,
      "join_scope": "unsupported_league_key",
      "join_detail": "liga_europy"
    },
    {
      "dataset_label": "liga_konferencji-2223",
      "ids_name": "liga_konferencji_2223",
      "ids_file": "present",
      "ids_event_count": 125,
      "join_scope": "unsupported_league_key",
      "join_detail": "liga_konferencji"
    },
    {
      "dataset_label": "liga_konferencji-2324",
      "ids_name": "liga_konferencji_2324",
      "ids_file": "present",
      "ids_event_count": 125,
      "join_scope": "unsupported_league_key",
      "join_detail": "liga_konferencji"
    },
    {
      "dataset_label": "liga_konferencji-2425",
      "ids_name": "liga_konferencji_2425",
      "ids_file": "present",
      "ids_event_count": 135,
      "join_scope": "unsupported_league_key",
      "join_detail": "liga_konferencji"
    },
    {
      "dataset_label": "liga_konferencji-2526",
      "ids_name": "liga_konferencji_2526",
      "ids_file": "present",
      "ids_event_count": 134,
      "join_scope": "unsupported_league_key",
      "join_detail": "liga_konferencji"
    },
    {
      "dataset_label": "puchar_polski-2223",
      "ids_name": "puchar_polski_2223",
      "ids_file": "present",
      "ids_event_count": 69,
      "join_scope": "unsupported_league_key",
      "join_detail": "puchar_polski"
    },
    {
      "dataset_label": "puchar_polski-2324",
      "ids_name": "puchar_polski_2324",
      "ids_file": "present",
      "ids_event_count": 69,
      "join_scope": "unsupported_league_key",
      "join_detail": "puchar_polski"
    },
    {
      "dataset_label": "puchar_polski-2425",
      "ids_name": "puchar_polski_2425",
      "ids_file": "present",
      "ids_event_count": 69,
      "join_scope": "unsupported_league_key",
      "join_detail": "puchar_polski"
    },
    {
      "dataset_label": "puchar_polski-2526",
      "ids_name": "puchar_polski_2526",
      "ids_file": "present",
      "ids_event_count": 69,
      "join_scope": "unsupported_league_key",
      "join_detail": "puchar_polski"
    },
    {
      "dataset_label": "puchar_czech-2223",
      "ids_name": "puchar_czech_2223",
      "ids_file": "present",
      "ids_event_count": 103,
      "join_scope": "unsupported_league_key",
      "join_detail": "puchar_czech"
    },
    {
      "dataset_label": "puchar_czech-2324",
      "ids_name": "puchar_czech_2324",
      "ids_file": "present",
      "ids_event_count": 116,
      "join_scope": "unsupported_league_key",
      "join_detail": "puchar_czech"
    },
    {
      "dataset_label": "puchar_czech-2425",
      "ids_name": "puchar_czech_2425",
      "ids_file": "present",
      "ids_event_count": 104,
      "join_scope": "unsupported_league_key",
      "join_detail": "puchar_czech"
    },
    {
      "dataset_label": "puchar_czech-2526",
      "ids_name": "puchar_czech_2526",
      "ids_file": "present",
      "ids_event_count": 124,
      "join_scope": "unsupported_league_key",
      "join_detail": "puchar_czech"
    },
    {
      "dataset_label": "taca_de_portugal-2223",
      "ids_name": "taca_de_portugal_2223",
      "ids_file": "present",
      "ids_event_count": 148,
      "join_scope": "unsupported_league_key",
      "join_detail": "taca_de_portugal"
    },
    {
      "dataset_label": "taca_de_portugal-2324",
      "ids_name": "taca_de_portugal_2324",
      "ids_file": "present",
      "ids_event_count": 111,
      "join_scope": "unsupported_league_key",
      "join_detail": "taca_de_portugal"
    },
    {
      "dataset_label": "taca_de_portugal-2425",
      "ids_name": "taca_de_portugal_2425",
      "ids_file": "present",
      "ids_event_count": 110,
      "join_scope": "unsupported_league_key",
      "join_detail": "taca_de_portugal"
    },
    {
      "dataset_label": "taca_de_portugal-2526",
      "ids_name": "taca_de_portugal_2526",
      "ids_file": "present",
      "ids_event_count": 112,
      "join_scope": "unsupported_league_key",
      "join_detail": "taca_de_portugal"
    },
    {
      "dataset_label": "copa_del_rey-2223",
      "ids_name": "copa_del_rey_2223",
      "ids_file": "present",
      "ids_event_count": 126,
      "join_scope": "unsupported_league_key",
      "join_detail": "copa_del_rey"
    },
    {
      "dataset_label": "copa_del_rey-2324",
      "ids_name": "copa_del_rey_2324",
      "ids_file": "present",
      "ids_event_count": 116,
      "join_scope": "unsupported_league_key",
      "join_detail": "copa_del_rey"
    },
    {
      "dataset_label": "copa_del_rey-2425",
      "ids_name": "copa_del_rey_2425",
      "ids_file": "present",
      "ids_event_count": 116,
      "join_scope": "unsupported_league_key",
      "join_detail": "copa_del_rey"
    },
    {
      "dataset_label": "copa_del_rey-2526",
      "ids_name": "copa_del_rey_2526",
      "ids_file": "present",
      "ids_event_count": 127,
      "join_scope": "unsupported_league_key",
      "join_detail": "copa_del_rey"
    },
    {
      "dataset_label": "coppa_italia-2223",
      "ids_name": "coppa_italia_2223",
      "ids_file": "present",
      "ids_event_count": 45,
      "join_scope": "unsupported_league_key",
      "join_detail": "coppa_italia"
    },
    {
      "dataset_label": "coppa_italia-2324",
      "ids_name": "coppa_italia_2324",
      "ids_file": "present",
      "ids_event_count": 45,
      "join_scope": "unsupported_league_key",
      "join_detail": "coppa_italia"
    },
    {
      "dataset_label": "coppa_italia-2425",
      "ids_name": "coppa_italia_2425",
      "ids_file": "present",
      "ids_event_count": 45,
      "join_scope": "unsupported_league_key",
      "join_detail": "coppa_italia"
    },
    {
      "dataset_label": "coppa_italia-2526",
      "ids_name": "coppa_italia_2526",
      "ids_file": "present",
      "ids_event_count": 45,
      "join_scope": "unsupported_league_key",
      "join_detail": "coppa_italia"
    },
    {
      "dataset_label": "fa_cup-2223",
      "ids_name": "fa_cup_2223",
      "ids_file": "present",
      "ids_event_count": 106,
      "join_scope": "engsoccerdata_facup",
      "join_detail": null,
      "cli": "ENGSD",
      "division": "FACUP"
    },
    {
      "dataset_label": "fa_cup-2324",
      "ids_name": "fa_cup_2324",
      "ids_file": "present",
      "ids_event_count": 109,
      "join_scope": "engsoccerdata_facup",
      "join_detail": null,
      "cli": "ENGSD",
      "division": "FACUP"
    },
    {
      "dataset_label": "fa_cup-2425",
      "ids_name": "fa_cup_2425",
      "ids_file": "present",
      "ids_event_count": 123,
      "join_scope": "engsoccerdata_facup",
      "join_detail": null,
      "cli": "ENGSD",
      "division": "FACUP"
    },
    {
      "dataset_label": "fa_cup-2526",
      "ids_name": "fa_cup_2526",
      "ids_file": "present",
      "ids_event_count": 130,
      "join_scope": "engsoccerdata_facup",
      "join_detail": null,
      "cli": "ENGSD",
      "division": "FACUP"
    },
    {
      "dataset_label": "carabao_cup-2223",
      "ids_name": "carabao_cup_2223",
      "ids_file": "present",
      "ids_event_count": 93,
      "join_scope": "engsoccerdata_leaguecup",
      "join_detail": null,
      "cli": "ENGSD",
      "division": "CARABAO"
    },
    {
      "dataset_label": "carabao_cup-2324",
      "ids_name": "carabao_cup_2324",
      "ids_file": "present",
      "ids_event_count": 93,
      "join_scope": "engsoccerdata_leaguecup",
      "join_detail": null,
      "cli": "ENGSD",
      "division": "CARABAO"
    },
    {
      "dataset_label": "carabao_cup-2425",
      "ids_name": "carabao_cup_2425",
      "ids_file": "present",
      "ids_event_count": 93,
      "join_scope": "engsoccerdata_leaguecup",
      "join_detail": null,
      "cli": "ENGSD",
      "division": "CARABAO"
    },
    {
      "dataset_label": "carabao_cup-2526",
      "ids_name": "carabao_cup_2526",
      "ids_file": "present",
      "ids_event_count": 93,
      "join_scope": "engsoccerdata_leaguecup",
      "join_detail": null,
      "cli": "ENGSD",
      "division": "CARABAO"
    },
    {
      "dataset_label": "dfb_pokal-2223",
      "ids_name": "dfb_pokal_2223",
      "ids_file": "present",
      "ids_event_count": 63,
      "join_scope": "unsupported_league_key",
      "join_detail": "dfb_pokal"
    },
    {
      "dataset_label": "dfb_pokal-2324",
      "ids_name": "dfb_pokal_2324",
      "ids_file": "present",
      "ids_event_count": 63,
      "join_scope": "unsupported_league_key",
      "join_detail": "dfb_pokal"
    },
    {
      "dataset_label": "dfb_pokal-2425",
      "ids_name": "dfb_pokal_2425",
      "ids_file": "present",
      "ids_event_count": 63,
      "join_scope": "unsupported_league_key",
      "join_detail": "dfb_pokal"
    },
    {
      "dataset_label": "dfb_pokal-2526",
      "ids_name": "dfb_pokal_2526",
      "ids_file": "present",
      "ids_event_count": 63,
      "join_scope": "unsupported_league_key",
      "join_detail": "dfb_pokal"
    },
    {
      "dataset_label": "coupe_de_france-2223",
      "ids_name": "coupe_de_france_2223",
      "ids_file": "present",
      "ids_event_count": 107,
      "join_scope": "unsupported_league_key",
      "join_detail": "coupe_de_france"
    },
    {
      "dataset_label": "coupe_de_france-2324",
      "ids_name": "coupe_de_france_2324",
      "ids_file": "present",
      "ids_event_count": 111,
      "join_scope": "unsupported_league_key",
      "join_detail": "coupe_de_france"
    },
    {
      "dataset_label": "coupe_de_france-2425",
      "ids_name": "coupe_de_france_2425",
      "ids_file": "present",
      "ids_event_count": 108,
      "join_scope": "unsupported_league_key",
      "join_detail": "coupe_de_france"
    },
    {
      "dataset_label": "coupe_de_france-2526",
      "ids_name": "coupe_de_france_2526",
      "ids_file": "present",
      "ids_event_count": 109,
      "join_scope": "unsupported_league_key",
      "join_detail": "coupe_de_france"
    },
    {
      "dataset_label": "knvb_beker-2223",
      "ids_name": "knvb_beker_2223",
      "ids_file": "present",
      "ids_event_count": 85,
      "join_scope": "unsupported_league_key",
      "join_detail": "knvb_beker"
    },
    {
      "dataset_label": "knvb_beker-2324",
      "ids_name": "knvb_beker_2324",
      "ids_file": "present",
      "ids_event_count": 109,
      "join_scope": "unsupported_league_key",
      "join_detail": "knvb_beker"
    },
    {
      "dataset_label": "knvb_beker-2425",
      "ids_name": "knvb_beker_2425",
      "ids_file": "present",
      "ids_event_count": 109,
      "join_scope": "unsupported_league_key",
      "join_detail": "knvb_beker"
    },
    {
      "dataset_label": "knvb_beker-2526",
      "ids_name": "knvb_beker_2526",
      "ids_file": "present",
      "ids_event_count": 109,
      "join_scope": "unsupported_league_key",
      "join_detail": "knvb_beker"
    },
    {
      "dataset_label": "puchar_belgii-2223",
      "ids_name": "puchar_belgii_2223",
      "ids_file": "present",
      "ids_event_count": 121,
      "join_scope": "unsupported_league_key",
      "join_detail": "puchar_belgii"
    },
    {
      "dataset_label": "puchar_belgii-2324",
      "ids_name": "puchar_belgii_2324",
      "ids_file": "present",
      "ids_event_count": 109,
      "join_scope": "unsupported_league_key",
      "join_detail": "puchar_belgii"
    },
    {
      "dataset_label": "puchar_belgii-2425",
      "ids_name": "puchar_belgii_2425",
      "ids_file": "present",
      "ids_event_count": 153,
      "join_scope": "unsupported_league_key",
      "join_detail": "puchar_belgii"
    },
    {
      "dataset_label": "puchar_belgii-2526",
      "ids_name": "puchar_belgii_2526",
      "ids_file": "present",
      "ids_event_count": 33,
      "join_scope": "unsupported_league_key",
      "join_detail": "puchar_belgii"
    },
    {
      "dataset_label": "puchar_grecji-2223",
      "ids_name": "puchar_grecji_2223",
      "ids_file": "present",
      "ids_event_count": 97,
      "join_scope": "unsupported_league_key",
      "join_detail": "puchar_grecji"
    },
    {
      "dataset_label": "puchar_grecji-2324",
      "ids_name": "puchar_grecji_2324",
      "ids_file": "present",
      "ids_event_count": 92,
      "join_scope": "unsupported_league_key",
      "join_detail": "puchar_grecji"
    },
    {
      "dataset_label": "puchar_grecji-2425",
      "ids_name": "puchar_grecji_2425",
      "ids_file": "present",
      "ids_event_count": 93,
      "join_scope": "unsupported_league_key",
      "join_detail": "puchar_grecji"
    },
    {
      "dataset_label": "puchar_grecji-2526",
      "ids_name": "puchar_grecji_2526",
      "ids_file": "present",
      "ids_event_count": 64,
      "join_scope": "unsupported_league_key",
      "join_detail": "puchar_grecji"
    },
    {
      "dataset_label": "puchar_turcji-2223",
      "ids_name": "puchar_turcji_2223",
      "ids_file": "present",
      "ids_event_count": 123,
      "join_scope": "unsupported_league_key",
      "join_detail": "puchar_turcji"
    },
    {
      "dataset_label": "puchar_turcji-2324",
      "ids_name": "puchar_turcji_2324",
      "ids_file": "present",
      "ids_event_count": 120,
      "join_scope": "unsupported_league_key",
      "join_detail": "puchar_turcji"
    },
    {
      "dataset_label": "puchar_turcji-2425",
      "ids_name": "puchar_turcji_2425",
      "ids_file": "present",
      "ids_event_count": 126,
      "join_scope": "unsupported_league_key",
      "join_detail": "puchar_turcji"
    },
    {
      "dataset_label": "puchar_turcji-2526",
      "ids_name": "puchar_turcji_2526",
      "ids_file": "present",
      "ids_event_count": 130,
      "join_scope": "unsupported_league_key",
      "join_detail": "puchar_turcji"
    }
  ],
  "ids_never_attempted_dataset_labels": [
    "copa_del_rey-2223",
    "copa_del_rey-2324",
    "copa_del_rey-2425",
    "copa_del_rey-2526",
    "coppa_italia-2223",
    "coppa_italia-2324",
    "coppa_italia-2425",
    "coppa_italia-2526",
    "coupe_de_france-2223",
    "coupe_de_france-2324",
    "coupe_de_france-2425",
    "coupe_de_france-2526",
    "dfb_pokal-2223",
    "dfb_pokal-2324",
    "dfb_pokal-2425",
    "dfb_pokal-2526",
    "knvb_beker-2223",
    "knvb_beker-2324",
    "knvb_beker-2425",
    "knvb_beker-2526",
    "liga_europy-2223",
    "liga_europy-2324",
    "liga_europy-2425",
    "liga_europy-2526",
    "liga_konferencji-2223",
    "liga_konferencji-2324",
    "liga_konferencji-2425",
    "liga_konferencji-2526",
    "liga_mistrzow-2223",
    "liga_mistrzow-2324",
    "liga_mistrzow-2425",
    "liga_mistrzow-2526",
    "puchar_belgii-2223",
    "puchar_belgii-2324",
    "puchar_belgii-2425",
    "puchar_belgii-2526",
    "puchar_czech-2223",
    "puchar_czech-2324",
    "puchar_czech-2425",
    "puchar_czech-2526",
    "puchar_grecji-2223",
    "puchar_grecji-2324",
    "puchar_grecji-2425",
    "puchar_grecji-2526",
    "puchar_polski-2223",
    "puchar_polski-2324",
    "puchar_polski-2425",
    "puchar_polski-2526",
    "puchar_turcji-2223",
    "puchar_turcji-2324",
    "puchar_turcji-2425",
    "puchar_turcji-2526",
    "taca_de_portugal-2223",
    "taca_de_portugal-2324",
    "taca_de_portugal-2425",
    "taca_de_portugal-2526"
  ],
  "forensics_df_st_li": [
    {
      "sample_path_relative": "data/raw/flashscore/polska/ekstraklasa/2526/matches/YsxcdXdm/df_st_1_YsxcdXdm.txt",
      "first_bytes_hex": "5345c3b74d65637ac2ac7e5346c3b7546f70207374617479",
      "byte_len_scanned": 6476,
      "has_tilde_aa": false,
      "has_marker_px_latin1": false,
      "has_marker_px_utf8": false
    },
    {
      "sample_path_relative": "data/raw/flashscore/polska/ekstraklasa/2526/matches/hA1OsYsf/df_st_1_hA1OsYsf.txt",
      "first_bytes_hex": "5345c3b74d65637ac2ac7e5346c3b7546f70207374617479",
      "byte_len_scanned": 6358,
      "has_tilde_aa": false,
      "has_marker_px_latin1": false,
      "has_marker_px_utf8": false
    },
    {
      "sample_path_relative": "data/raw/flashscore/polska/ekstraklasa/2526/matches/EceQ1gZP/df_st_1_EceQ1gZP.txt",
      "first_bytes_hex": "5345c3b74d65637ac2ac7e5346c3b7546f70207374617479",
      "byte_len_scanned": 6528,
      "has_tilde_aa": false,
      "has_marker_px_latin1": false,
      "has_marker_px_utf8": false
    },
    {
      "sample_path_relative": "data/raw/flashscore/polska/ekstraklasa/2526/matches/WfDFqfDs/df_st_1_WfDFqfDs.txt",
      "first_bytes_hex": "5345c3b74d65637ac2ac7e5346c3b7546f70207374617479",
      "byte_len_scanned": 6516,
      "has_tilde_aa": false,
      "has_marker_px_latin1": false,
      "has_marker_px_utf8": false
    },
    {
      "sample_path_relative": "data/raw/flashscore/polska/ekstraklasa/2526/matches/QyFVuCC6/df_st_1_QyFVuCC6.txt",
      "first_bytes_hex": "5345c3b74d65637ac2ac7e5346c3b7546f70207374617479",
      "byte_len_scanned": 6402,
      "has_tilde_aa": false,
      "has_marker_px_latin1": false,
      "has_marker_px_utf8": false
    },
    {
      "sample_path_relative": "data/raw/flashscore/polska/ekstraklasa/2526/matches/0fTDhkdC/df_st_1_0fTDhkdC.txt",
      "first_bytes_hex": "5345c3b74d65637ac2ac7e5346c3b7546f70207374617479",
      "byte_len_scanned": 6612,
      "has_tilde_aa": false,
      "has_marker_px_latin1": false,
      "has_marker_px_utf8": false
    },
    {
      "sample_path_relative": "data/raw/flashscore/polska/ekstraklasa/2526/matches/M38vvjsJ/df_st_1_M38vvjsJ.txt",
      "first_bytes_hex": "5345c3b74d65637ac2ac7e5346c3b7546f70207374617479",
      "byte_len_scanned": 6355,
      "has_tilde_aa": false,
      "has_marker_px_latin1": false,
      "has_marker_px_utf8": false
    },
    {
      "sample_path_relative": "data/raw/flashscore/polska/ekstraklasa/2526/matches/0CMqkGkK/df_st_1_0CMqkGkK.txt",
      "first_bytes_hex": "5345c3b74d65637ac2ac7e5346c3b7546f70207374617479",
      "byte_len_scanned": 6397,
      "has_tilde_aa": false,
      "has_marker_px_latin1": false,
      "has_marker_px_utf8": false
    }
  ],
  "notes": "skipped_no_row_build_semantics matches build_integration_supplement counter (meta present but lookup_fd_row returned None, including unix_ts is None).",
  "lookup_miss_sample_meta": {
    "preset": "lookup_miss_valid_unix",
    "population": 982,
    "sample_size": 200,
    "seed": 42,
    "stratification": "proportional_largest_remainder",
    "diagnostic_wide_radius_days": 7,
    "sampling_skipped": false,
    "classified_full_population": false,
    "taxonomy_reference": "diagnose_fd_row_miss in football_ai.integration.join_football_data (wide uses k∈[-R,R] excluding {-1,0,1})"
  },
  "lookup_miss_diagnosis_sample": [
    {
      "event_id": "zH3H9cBP",
      "dataset_label": "carabao_cup-2324",
      "unix_kickoff": 1691520300,
      "category": "csv_index_empty"
    },
    {
      "event_id": "WSQqW4p2",
      "dataset_label": "carabao_cup-2425",
      "unix_kickoff": 1723574700,
      "category": "csv_index_empty"
    },
    {
      "event_id": "GdY8jmnJ",
      "dataset_label": "carabao_cup-2324",
      "unix_kickoff": 1695840300,
      "category": "csv_index_empty"
    },
    {
      "event_id": "pWQ6LC1N",
      "dataset_label": "carabao_cup-2425",
      "unix_kickoff": 1724784300,
      "category": "csv_index_empty"
    },
    {
      "event_id": "WbyBa6hn",
      "dataset_label": "fa_cup-2223",
      "unix_kickoff": 1673094600,
      "category": "csv_index_empty"
    },
    {
      "event_id": "WjTd3Lm3",
      "dataset_label": "fa_cup-2526",
      "unix_kickoff": 1764963000,
      "category": "csv_index_empty"
    },
    {
      "event_id": "GKA1PoOi",
      "dataset_label": "fa_cup-2425",
      "unix_kickoff": 1736699400,
      "category": "csv_index_empty"
    },
    {
      "event_id": "nLjR1aln",
      "dataset_label": "fa_cup-2223",
      "unix_kickoff": 1677699900,
      "category": "csv_index_empty"
    },
    {
      "event_id": "hCODSnKa",
      "dataset_label": "ekstraklasa-2526",
      "unix_kickoff": 1771869600,
      "category": "no_ordered_hit_after_pmR",
      "diagnostic_wide_radius_days": 7
    },
    {
      "event_id": "YcnQbdbm",
      "dataset_label": "fa_cup-2425",
      "unix_kickoff": 1739113200,
      "category": "csv_index_empty"
    },
    {
      "event_id": "fDO0fYhT",
      "dataset_label": "fa_cup-2425",
      "unix_kickoff": 1730559600,
      "category": "csv_index_empty"
    },
    {
      "event_id": "lWFC2f17",
      "dataset_label": "carabao_cup-2223",
      "unix_kickoff": 1667936700,
      "category": "csv_index_empty"
    },
    {
      "event_id": "nBoN3mX9",
      "dataset_label": "fa_cup-2324",
      "unix_kickoff": 1706452200,
      "category": "csv_index_empty"
    },
    {
      "event_id": "nDGCzXV4",
      "dataset_label": "fa_cup-2223",
      "unix_kickoff": 1677612600,
      "category": "csv_index_empty"
    },
    {
      "event_id": "tYrqPRPD",
      "dataset_label": "fa_cup-2223",
      "unix_kickoff": 1675000800,
      "category": "csv_index_empty"
    },
    {
      "event_id": "WEFGSvmd",
      "dataset_label": "carabao_cup-2526",
      "unix_kickoff": 1755110700,
      "category": "csv_index_empty"
    },
    {
      "event_id": "6FtJSA1B",
      "dataset_label": "fa_cup-2425",
      "unix_kickoff": 1743337800,
      "category": "csv_index_empty"
    },
    {
      "event_id": "lUnwQZ41",
      "dataset_label": "fa_cup-2324",
      "unix_kickoff": 1704744900,
      "category": "csv_index_empty"
    },
    {
      "event_id": "bTRJf3RS",
      "dataset_label": "fa_cup-2324",
      "unix_kickoff": 1707336000,
      "category": "csv_index_empty"
    },
    {
      "event_id": "rXyiNLI0",
      "dataset_label": "ekstraklasa-2526",
      "unix_kickoff": 1777822200,
      "category": "no_ordered_hit_after_pmR",
      "diagnostic_wide_radius_days": 7
    },
    {
      "event_id": "h8lQ7R0N",
      "dataset_label": "ekstraklasa-2526",
      "unix_kickoff": 1774206900,
      "category": "no_ordered_hit_after_pmR",
      "diagnostic_wide_radius_days": 7
    },
    {
      "event_id": "pWCYPYdn",
      "dataset_label": "fa_cup-2425",
      "unix_kickoff": 1738958400,
      "category": "csv_index_empty"
    },
    {
      "event_id": "4GchYt7M",
      "dataset_label": "fa_cup-2425",
      "unix_kickoff": 1736685000,
      "category": "csv_index_empty"
    },
    {
      "event_id": "EkqxE9x0",
      "dataset_label": "carabao_cup-2425",
      "unix_kickoff": 1724785200,
      "category": "csv_index_empty"
    },
    {
      "event_id": "KzdBlM9F",
      "dataset_label": "carabao_cup-2526",
      "unix_kickoff": 1755024300,
      "category": "csv_index_empty"
    },
    {
      "event_id": "jZrVvjm7",
      "dataset_label": "carabao_cup-2324",
      "unix_kickoff": 1695840300,
      "category": "csv_index_empty"
    },
    {
      "event_id": "MwmHgKaN",
      "dataset_label": "carabao_cup-2425",
      "unix_kickoff": 1723574700,
      "category": "csv_index_empty"
    },
    {
      "event_id": "vkf6rY3C",
      "dataset_label": "fa_cup-2324",
      "unix_kickoff": 1706211900,
      "category": "csv_index_empty"
    },
    {
      "event_id": "fZaPZJ9I",
      "dataset_label": "carabao_cup-2223",
      "unix_kickoff": 1660070700,
      "category": "csv_index_empty"
    },
    {
      "event_id": "Iw65TfHE",
      "dataset_label": "fa_cup-2425",
      "unix_kickoff": 1740851100,
      "category": "csv_index_empty"
    },
    {
      "event_id": "INw8JNLs",
      "dataset_label": "fa_cup-2425",
      "unix_kickoff": 1730559600,
      "category": "csv_index_empty"
    },
    {
      "event_id": "697ha3El",
      "dataset_label": "carabao_cup-2425",
      "unix_kickoff": 1723662000,
      "category": "csv_index_empty"
    },
    {
      "event_id": "4bnoVrLt",
      "dataset_label": "fa_cup-2223",
      "unix_kickoff": 1670442300,
      "category": "csv_index_empty"
    },
    {
      "event_id": "CAW1NWMF",
      "dataset_label": "fa_cup-2425",
      "unix_kickoff": 1730559600,
      "category": "csv_index_empty"
    },
    {
      "event_id": "UZELZdyf",
      "dataset_label": "fa_cup-2526",
      "unix_kickoff": 1768938300,
      "category": "csv_index_empty"
    },
    {
      "event_id": "j1g1wY8b",
      "dataset_label": "ekstraklasa-2526",
      "unix_kickoff": 1778265000,
      "category": "no_ordered_hit_after_pmR",
      "diagnostic_wide_radius_days": 7
    },
    {
      "event_id": "l6n6lTK0",
      "dataset_label": "carabao_cup-2324",
      "unix_kickoff": 1693334700,
      "category": "csv_index_empty"
    },
    {
      "event_id": "6omle85S",
      "dataset_label": "carabao_cup-2526",
      "unix_kickoff": 1758740400,
      "category": "csv_index_empty"
    },
    {
      "event_id": "vmNvRnvg",
      "dataset_label": "carabao_cup-2425",
      "unix_kickoff": 1730319300,
      "category": "csv_index_empty"
    },
    {
      "event_id": "Ei2ZTQz9",
      "dataset_label": "ekstraklasa-2526",
      "unix_kickoff": 1779552000,
      "category": "no_ordered_hit_after_pmR",
      "diagnostic_wide_radius_days": 7
    },
    {
      "event_id": "t4mBAAq9",
      "dataset_label": "fa_cup-2324",
      "unix_kickoff": 1699991100,
      "category": "csv_index_empty"
    },
    {
      "event_id": "lWw234cn",
      "dataset_label": "fa_cup-2526",
      "unix_kickoff": 1762009200,
      "category": "csv_index_empty"
    },
    {
      "event_id": "42pzPxQM",
      "dataset_label": "fa_cup-2526",
      "unix_kickoff": 1762095600,
      "category": "csv_index_empty"
    },
    {
      "event_id": "Olj71k0d",
      "dataset_label": "fa_cup-2425",
      "unix_kickoff": 1730559600,
      "category": "csv_index_empty"
    },
    {
      "event_id": "h8Euaj63",
      "dataset_label": "carabao_cup-2526",
      "unix_kickoff": 1758049200,
      "category": "csv_index_empty"
    },
    {
      "event_id": "I5YrW3rT",
      "dataset_label": "carabao_cup-2223",
      "unix_kickoff": 1661280300,
      "category": "csv_index_empty"
    },
    {
      "event_id": "pUikwmj4",
      "dataset_label": "fa_cup-2526",
      "unix_kickoff": 1771081200,
      "category": "csv_index_empty"
    },
    {
      "event_id": "UkFcN5Yj",
      "dataset_label": "ekstraklasa-2526",
      "unix_kickoff": 1765729800,
      "category": "no_ordered_hit_after_pmR",
      "diagnostic_wide_radius_days": 7
    },
    {
      "event_id": "4KwDffx2",
      "dataset_label": "carabao_cup-2425",
      "unix_kickoff": 1727290800,
      "category": "csv_index_empty"
    },
    {
      "event_id": "I5tIqhCC",
      "dataset_label": "carabao_cup-2526",
      "unix_kickoff": 1755024300,
      "category": "csv_index_empty"
    },
    {
      "event_id": "4UOCTsNq",
      "dataset_label": "ekstraklasa-2526",
      "unix_kickoff": 1775499300,
      "category": "no_ordered_hit_after_pmR",
      "diagnostic_wide_radius_days": 7
    },
    {
      "event_id": "I9bZ4O6l",
      "dataset_label": "fa_cup-2425",
      "unix_kickoff": 1730559600,
      "category": "csv_index_empty"
    },
    {
      "event_id": "Y1ScJwOo",
      "dataset_label": "carabao_cup-2223",
      "unix_kickoff": 1660070700,
      "category": "csv_index_empty"
    },
    {
      "event_id": "OnDH3sdF",
      "dataset_label": "fa_cup-2324",
      "unix_kickoff": 1704553200,
      "category": "csv_index_empty"
    },
    {
      "event_id": "vuPc0qb1",
      "dataset_label": "fa_cup-2324",
      "unix_kickoff": 1701529200,
      "category": "csv_index_empty"
    },
    {
      "event_id": "U9e1oWy1",
      "dataset_label": "fa_cup-2526",
      "unix_kickoff": 1762009200,
      "category": "csv_index_empty"
    },
    {
      "event_id": "2DvJ4UzC",
      "dataset_label": "fa_cup-2223",
      "unix_kickoff": 1679227200,
      "category": "csv_index_empty"
    },
    {
      "event_id": "p8SFMZNE",
      "dataset_label": "fa_cup-2526",
      "unix_kickoff": 1771011900,
      "category": "csv_index_empty"
    },
    {
      "event_id": "rkTI1LQR",
      "dataset_label": "fa_cup-2324",
      "unix_kickoff": 1704553200,
      "category": "csv_index_empty"
    },
    {
      "event_id": "WfTyZpOB",
      "dataset_label": "carabao_cup-2324",
      "unix_kickoff": 1698867900,
      "category": "csv_index_empty"
    },
    {
      "event_id": "nFcEtCYO",
      "dataset_label": "fa_cup-2324",
      "unix_kickoff": 1706298300,
      "category": "csv_index_empty"
    },
    {
      "event_id": "Cx3knG4m",
      "dataset_label": "fa_cup-2324",
      "unix_kickoff": 1706450400,
      "category": "csv_index_empty"
    },
    {
      "event_id": "femlyACb",
      "dataset_label": "fa_cup-2526",
      "unix_kickoff": 1767987000,
      "category": "csv_index_empty"
    },
    {
      "event_id": "tQ0TDxwR",
      "dataset_label": "carabao_cup-2526",
      "unix_kickoff": 1755111600,
      "category": "csv_index_empty"
    },
    {
      "event_id": "t6jcLvWF",
      "dataset_label": "ekstraklasa-2526",
      "unix_kickoff": 1777046400,
      "category": "no_ordered_hit_after_pmR",
      "diagnostic_wide_radius_days": 7
    },
    {
      "event_id": "Cn4ANPh4",
      "dataset_label": "fa_cup-2425",
      "unix_kickoff": 1736596800,
      "category": "csv_index_empty"
    },
    {
      "event_id": "vyoZBtbf",
      "dataset_label": "carabao_cup-2425",
      "unix_kickoff": 1723575600,
      "category": "csv_index_empty"
    },
    {
      "event_id": "GSSzGnvJ",
      "dataset_label": "fa_cup-2223",
      "unix_kickoff": 1673195400,
      "category": "csv_index_empty"
    },
    {
      "event_id": "SUURQlWN",
      "dataset_label": "fa_cup-2425",
      "unix_kickoff": 1743250500,
      "category": "csv_index_empty"
    },
    {
      "event_id": "vuu5fBRa",
      "dataset_label": "ekstraklasa-2526",
      "unix_kickoff": 1776099600,
      "category": "no_ordered_hit_after_pmR",
      "diagnostic_wide_radius_days": 7
    },
    {
      "event_id": "KbYVJVpC",
      "dataset_label": "fa_cup-2324",
      "unix_kickoff": 1702410300,
      "category": "csv_index_empty"
    },
    {
      "event_id": "Ofaf72wq",
      "dataset_label": "carabao_cup-2425",
      "unix_kickoff": 1734638400,
      "category": "csv_index_empty"
    },
    {
      "event_id": "rNOJ1bbn",
      "dataset_label": "ekstraklasa-2526",
      "unix_kickoff": 1769963400,
      "category": "no_ordered_hit_after_pmR",
      "diagnostic_wide_radius_days": 7
    },
    {
      "event_id": "x6Z4iTWC",
      "dataset_label": "carabao_cup-2324",
      "unix_kickoff": 1695840300,
      "category": "csv_index_empty"
    },
    {
      "event_id": "hnyNEsC2",
      "dataset_label": "carabao_cup-2223",
      "unix_kickoff": 1661280300,
      "category": "csv_index_empty"
    },
    {
      "event_id": "8xQblJOB",
      "dataset_label": "carabao_cup-2223",
      "unix_kickoff": 1660070700,
      "category": "csv_index_empty"
    },
    {
      "event_id": "b1DI2lxA",
      "dataset_label": "ekstraklasa-2526",
      "unix_kickoff": 1778947200,
      "category": "no_ordered_hit_after_pmR",
      "diagnostic_wide_radius_days": 7
    },
    {
      "event_id": "4j0I9SED",
      "dataset_label": "ekstraklasa-2526",
      "unix_kickoff": 1773421200,
      "category": "no_ordered_hit_after_pmR",
      "diagnostic_wide_radius_days": 7
    },
    {
      "event_id": "ABX0AAsK",
      "dataset_label": "carabao_cup-2324",
      "unix_kickoff": 1693421100,
      "category": "csv_index_empty"
    },
    {
      "event_id": "bPy9vrn4",
      "dataset_label": "carabao_cup-2425",
      "unix_kickoff": 1727289900,
      "category": "csv_index_empty"
    },
    {
      "event_id": "KbvGffoo",
      "dataset_label": "carabao_cup-2223",
      "unix_kickoff": 1660070700,
      "category": "csv_index_empty"
    },
    {
      "event_id": "IwQYANhc",
      "dataset_label": "ekstraklasa-2526",
      "unix_kickoff": 1770549300,
      "category": "no_ordered_hit_after_pmR",
      "diagnostic_wide_radius_days": 7
    },
    {
      "event_id": "zo9kELFj",
      "dataset_label": "fa_cup-2425",
      "unix_kickoff": 1736451900,
      "category": "csv_index_empty"
    },
    {
      "event_id": "xEoKc0RN",
      "dataset_label": "fa_cup-2526",
      "unix_kickoff": 1762009200,
      "category": "csv_index_empty"
    },
    {
      "event_id": "0ERgymEd",
      "dataset_label": "carabao_cup-2526",
      "unix_kickoff": 1758653100,
      "category": "csv_index_empty"
    },
    {
      "event_id": "bcaYVscE",
      "dataset_label": "carabao_cup-2526",
      "unix_kickoff": 1756321200,
      "category": "csv_index_empty"
    },
    {
      "event_id": "hzeTFV7m",
      "dataset_label": "carabao_cup-2425",
      "unix_kickoff": 1724784300,
      "category": "csv_index_empty"
    },
    {
      "event_id": "r5msoJ7g",
      "dataset_label": "fa_cup-2324",
      "unix_kickoff": 1707248700,
      "category": "csv_index_empty"
    },
    {
      "event_id": "6kyhlf9r",
      "dataset_label": "carabao_cup-2526",
      "unix_kickoff": 1758653100,
      "category": "csv_index_empty"
    },
    {
      "event_id": "KG1FJodg",
      "dataset_label": "carabao_cup-2324",
      "unix_kickoff": 1703102400,
      "category": "csv_index_empty"
    },
    {
      "event_id": "Es7dtqhO",
      "dataset_label": "fa_cup-2223",
      "unix_kickoff": 1673103600,
      "category": "csv_index_empty"
    },
    {
      "event_id": "Gp2m3aVe",
      "dataset_label": "carabao_cup-2324",
      "unix_kickoff": 1706040000,
      "category": "csv_index_empty"
    },
    {
      "event_id": "llBKxDl7",
      "dataset_label": "fa_cup-2324",
      "unix_kickoff": 1704636000,
      "category": "csv_index_empty"
    },
    {
      "event_id": "nLM33cBE",
      "dataset_label": "fa_cup-2526",
      "unix_kickoff": 1760467500,
      "category": "csv_index_empty"
    },
    {
      "event_id": "KUrgZen9",
      "dataset_label": "carabao_cup-2526",
      "unix_kickoff": 1756233900,
      "category": "csv_index_empty"
    },
    {
      "event_id": "EeUwcjBE",
      "dataset_label": "carabao_cup-2223",
      "unix_kickoff": 1660157100,
      "category": "csv_index_empty"
    },
    {
      "event_id": "AuuTz7ga",
      "dataset_label": "carabao_cup-2324",
      "unix_kickoff": 1698867900,
      "category": "csv_index_empty"
    },
    {
      "event_id": "ddgIp3cM",
      "dataset_label": "carabao_cup-2223",
      "unix_kickoff": 1661280300,
      "category": "csv_index_empty"
    },
    {
      "event_id": "dY0SOQjI",
      "dataset_label": "carabao_cup-2425",
      "unix_kickoff": 1724784300,
      "category": "csv_index_empty"
    },
    {
      "event_id": "8bwsZ3aM",
      "dataset_label": "ekstraklasa-2526",
      "unix_kickoff": 1775470500,
      "category": "no_ordered_hit_after_pmR",
      "diagnostic_wide_radius_days": 7
    },
    {
      "event_id": "nTOK8lOd",
      "dataset_label": "carabao_cup-2223",
      "unix_kickoff": 1671652800,
      "category": "csv_index_empty"
    },
    {
      "event_id": "IHdWm0z6",
      "dataset_label": "fa_cup-2223",
      "unix_kickoff": 1674909010,
      "category": "csv_index_empty"
    },
    {
      "event_id": "lQl9etVA",
      "dataset_label": "carabao_cup-2425",
      "unix_kickoff": 1723574700,
      "category": "csv_index_empty"
    },
    {
      "event_id": "2Ng9qA6D",
      "dataset_label": "fa_cup-2526",
      "unix_kickoff": 1762009200,
      "category": "csv_index_empty"
    },
    {
      "event_id": "AuXNt7Fj",
      "dataset_label": "ekstraklasa-2526",
      "unix_kickoff": 1778947200,
      "category": "no_ordered_hit_after_pmR",
      "diagnostic_wide_radius_days": 7
    },
    {
      "event_id": "pbXuY4wI",
      "dataset_label": "carabao_cup-2324",
      "unix_kickoff": 1698781500,
      "category": "csv_index_empty"
    },
    {
      "event_id": "xnkQVJhb",
      "dataset_label": "fa_cup-2324",
      "unix_kickoff": 1701719100,
      "category": "csv_index_empty"
    },
    {
      "event_id": "Of3np5eT",
      "dataset_label": "fa_cup-2526",
      "unix_kickoff": 1768057200,
      "category": "csv_index_empty"
    },
    {
      "event_id": "v5CXomOn",
      "dataset_label": "fa_cup-2223",
      "unix_kickoff": 1673103600,
      "category": "csv_index_empty"
    },
    {
      "event_id": "fau8yp5s",
      "dataset_label": "carabao_cup-2223",
      "unix_kickoff": 1675281600,
      "category": "csv_index_empty"
    },
    {
      "event_id": "K4ewNJil",
      "dataset_label": "fa_cup-2526",
      "unix_kickoff": 1768057200,
      "category": "csv_index_empty"
    },
    {
      "event_id": "KdovsIpI",
      "dataset_label": "carabao_cup-2526",
      "unix_kickoff": 1758653100,
      "category": "csv_index_empty"
    },
    {
      "event_id": "jHBgCatH",
      "dataset_label": "fa_cup-2526",
      "unix_kickoff": 1762009200,
      "category": "csv_index_empty"
    },
    {
      "event_id": "0KhC2EWr",
      "dataset_label": "fa_cup-2526",
      "unix_kickoff": 1771162200,
      "category": "csv_index_empty"
    },
    {
      "event_id": "GWhRW2fp",
      "dataset_label": "fa_cup-2223",
      "unix_kickoff": 1669474800,
      "category": "csv_index_empty"
    },
    {
      "event_id": "zgwRvpgC",
      "dataset_label": "carabao_cup-2324",
      "unix_kickoff": 1693334700,
      "category": "csv_index_empty"
    },
    {
      "event_id": "0hQZcWe8",
      "dataset_label": "carabao_cup-2223",
      "unix_kickoff": 1660157100,
      "category": "csv_index_empty"
    },
    {
      "event_id": "nuTXRDvq",
      "dataset_label": "carabao_cup-2526",
      "unix_kickoff": 1756233000,
      "category": "csv_index_empty"
    },
    {
      "event_id": "QmFunza2",
      "dataset_label": "carabao_cup-2324",
      "unix_kickoff": 1693334700,
      "category": "csv_index_empty"
    },
    {
      "event_id": "j5Rxdj2L",
      "dataset_label": "fa_cup-2425",
      "unix_kickoff": 1732978800,
      "category": "csv_index_empty"
    },
    {
      "event_id": "pzJRntMF",
      "dataset_label": "fa_cup-2425",
      "unix_kickoff": 1736607600,
      "category": "csv_index_empty"
    },
    {
      "event_id": "v9bvEm56",
      "dataset_label": "ekstraklasa-2526",
      "unix_kickoff": 1771011000,
      "category": "no_ordered_hit_after_pmR",
      "diagnostic_wide_radius_days": 7
    },
    {
      "event_id": "pWhdu9NF",
      "dataset_label": "carabao_cup-2425",
      "unix_kickoff": 1723574700,
      "category": "csv_index_empty"
    },
    {
      "event_id": "4S3fD3PF",
      "dataset_label": "fa_cup-2526",
      "unix_kickoff": 1768047300,
      "category": "csv_index_empty"
    },
    {
      "event_id": "M3K02khf",
      "dataset_label": "carabao_cup-2526",
      "unix_kickoff": 1756233900,
      "category": "csv_index_empty"
    },
    {
      "event_id": "ATOMKhNE",
      "dataset_label": "ekstraklasa-2526",
      "unix_kickoff": 1772901000,
      "category": "no_ordered_hit_after_pmR",
      "diagnostic_wide_radius_days": 7
    },
    {
      "event_id": "4fOt91N9",
      "dataset_label": "ekstraklasa-2526",
      "unix_kickoff": 1770397200,
      "category": "no_ordered_hit_after_pmR",
      "diagnostic_wide_radius_days": 7
    },
    {
      "event_id": "fJBTGqMt",
      "dataset_label": "ekstraklasa-2526",
      "unix_kickoff": 1773582300,
      "category": "no_ordered_hit_after_pmR",
      "diagnostic_wide_radius_days": 7
    },
    {
      "event_id": "CCV9JR0d",
      "dataset_label": "carabao_cup-2425",
      "unix_kickoff": 1723574700,
      "category": "csv_index_empty"
    },
    {
      "event_id": "67Q73zn1",
      "dataset_label": "carabao_cup-2223",
      "unix_kickoff": 1668024000,
      "category": "csv_index_empty"
    },
    {
      "event_id": "z5DeGvgB",
      "dataset_label": "fa_cup-2324",
      "unix_kickoff": 1701459900,
      "category": "csv_index_empty"
    },
    {
      "event_id": "bi6ayqnT",
      "dataset_label": "fa_cup-2223",
      "unix_kickoff": 1669474800,
      "category": "csv_index_empty"
    },
    {
      "event_id": "MNbu1d8H",
      "dataset_label": "carabao_cup-2223",
      "unix_kickoff": 1660157100,
      "category": "csv_index_empty"
    },
    {
      "event_id": "CMIJYzOA",
      "dataset_label": "fa_cup-2324",
      "unix_kickoff": 1699990200,
      "category": "csv_index_empty"
    },
    {
      "event_id": "nHVoqg0K",
      "dataset_label": "fa_cup-2526",
      "unix_kickoff": 1775319300,
      "category": "csv_index_empty"
    },
    {
      "event_id": "KI8v5L0q",
      "dataset_label": "carabao_cup-2324",
      "unix_kickoff": 1706126400,
      "category": "csv_index_empty"
    },
    {
      "event_id": "AwtPMn3n",
      "dataset_label": "fa_cup-2425",
      "unix_kickoff": 1736683200,
      "category": "csv_index_empty"
    },
    {
      "event_id": "fkIpELB4",
      "dataset_label": "fa_cup-2526",
      "unix_kickoff": 1762009200,
      "category": "csv_index_empty"
    },
    {
      "event_id": "n7eBSewq",
      "dataset_label": "ekstraklasa-2526",
      "unix_kickoff": 1777207500,
      "category": "no_ordered_hit_after_pmR",
      "diagnostic_wide_radius_days": 7
    },
    {
      "event_id": "EV6wFhm5",
      "dataset_label": "carabao_cup-2324",
      "unix_kickoff": 1691606700,
      "category": "csv_index_empty"
    },
    {
      "event_id": "OxKmomWl",
      "dataset_label": "fa_cup-2223",
      "unix_kickoff": 1674918000,
      "category": "csv_index_empty"
    },
    {
      "event_id": "hvHsGDV6",
      "dataset_label": "carabao_cup-2223",
      "unix_kickoff": 1667936700,
      "category": "csv_index_empty"
    },
    {
      "event_id": "K2SSaZYn",
      "dataset_label": "fa_cup-2324",
      "unix_kickoff": 1706299200,
      "category": "csv_index_empty"
    },
    {
      "event_id": "G2g1DVWo",
      "dataset_label": "ekstraklasa-2526",
      "unix_kickoff": 1773505800,
      "category": "no_ordered_hit_after_pmR",
      "diagnostic_wide_radius_days": 7
    },
    {
      "event_id": "zy0Me0BD",
      "dataset_label": "fa_cup-2526",
      "unix_kickoff": 1765033200,
      "category": "csv_index_empty"
    },
    {
      "event_id": "2LjdZmsB",
      "dataset_label": "fa_cup-2526",
      "unix_kickoff": 1768047300,
      "category": "csv_index_empty"
    },
    {
      "event_id": "fq5UNPHT",
      "dataset_label": "fa_cup-2223",
      "unix_kickoff": 1669552200,
      "category": "csv_index_empty"
    },
    {
      "event_id": "jyAA4A7c",
      "dataset_label": "ekstraklasa-2526",
      "unix_kickoff": 1778947200,
      "category": "no_ordered_hit_after_pmR",
      "diagnostic_wide_radius_days": 7
    },
    {
      "event_id": "n1hhaOVo",
      "dataset_label": "carabao_cup-2425",
      "unix_kickoff": 1723574700,
      "category": "csv_index_empty"
    },
    {
      "event_id": "ALEAD0Tc",
      "dataset_label": "carabao_cup-2324",
      "unix_kickoff": 1691520300,
      "category": "csv_index_empty"
    },
    {
      "event_id": "vLtJYhhe",
      "dataset_label": "fa_cup-2526",
      "unix_kickoff": 1762009200,
      "category": "csv_index_empty"
    },
    {
      "event_id": "8O69Blp1",
      "dataset_label": "ekstraklasa-2526",
      "unix_kickoff": 1773573300,
      "category": "no_ordered_hit_after_pmR",
      "diagnostic_wide_radius_days": 7
    },
    {
      "event_id": "ziI1CFC4",
      "dataset_label": "ekstraklasa-2526",
      "unix_kickoff": 1769877000,
      "category": "no_ordered_hit_after_pmR",
      "diagnostic_wide_radius_days": 7
    },
    {
      "event_id": "WITqnYGk",
      "dataset_label": "ekstraklasa-2526",
      "unix_kickoff": 1773079200,
      "category": "no_ordered_hit_after_pmR",
      "diagnostic_wide_radius_days": 7
    },
    {
      "event_id": "0Cv7SI4C",
      "dataset_label": "fa_cup-2425",
      "unix_kickoff": 1730559600,
      "category": "csv_index_empty"
    },
    {
      "event_id": "lEIF1rWp",
      "dataset_label": "fa_cup-2425",
      "unix_kickoff": 1736607600,
      "category": "csv_index_empty"
    },
    {
      "event_id": "hEwFT58I",
      "dataset_label": "fa_cup-2223",
      "unix_kickoff": 1673103600,
      "category": "csv_index_empty"
    },
    {
      "event_id": "hvyaw5HG",
      "dataset_label": "fa_cup-2223",
      "unix_kickoff": 1669466700,
      "category": "csv_index_empty"
    },
    {
      "event_id": "Cp5Fge3B",
      "dataset_label": "fa_cup-2425",
      "unix_kickoff": 1730559600,
      "category": "csv_index_empty"
    },
    {
      "event_id": "86wLARgC",
      "dataset_label": "carabao_cup-2425",
      "unix_kickoff": 1730317500,
      "category": "csv_index_empty"
    },
    {
      "event_id": "n5fLgGoL",
      "dataset_label": "carabao_cup-2526",
      "unix_kickoff": 1758135600,
      "category": "csv_index_empty"
    },
    {
      "event_id": "ALvC1RhA",
      "dataset_label": "fa_cup-2223",
      "unix_kickoff": 1674918000,
      "category": "csv_index_empty"
    },
    {
      "event_id": "YyoC6GAe",
      "dataset_label": "fa_cup-2324",
      "unix_kickoff": 1710591300,
      "category": "csv_index_empty"
    },
    {
      "event_id": "hSIez4xT",
      "dataset_label": "fa_cup-2223",
      "unix_kickoff": 1675799100,
      "category": "csv_index_empty"
    },
    {
      "event_id": "bw1zAKS6",
      "dataset_label": "carabao_cup-2425",
      "unix_kickoff": 1723574700,
      "category": "csv_index_empty"
    },
    {
      "event_id": "S6GbU1aE",
      "dataset_label": "fa_cup-2526",
      "unix_kickoff": 1768057200,
      "category": "csv_index_empty"
    },
    {
      "event_id": "0AwseEcC",
      "dataset_label": "fa_cup-2425",
      "unix_kickoff": 1739026800,
      "category": "csv_index_empty"
    },
    {
      "event_id": "bqSSmQc2",
      "dataset_label": "carabao_cup-2526",
      "unix_kickoff": 1758049200,
      "category": "csv_index_empty"
    },
    {
      "event_id": "0Ecq0GNN",
      "dataset_label": "carabao_cup-2223",
      "unix_kickoff": 1660157100,
      "category": "csv_index_empty"
    },
    {
      "event_id": "MmI8jUPr",
      "dataset_label": "fa_cup-2425",
      "unix_kickoff": 1732978800,
      "category": "csv_index_empty"
    },
    {
      "event_id": "EZErsSug",
      "dataset_label": "fa_cup-2324",
      "unix_kickoff": 1704398400,
      "category": "csv_index_empty"
    },
    {
      "event_id": "ddZgPsnA",
      "dataset_label": "carabao_cup-2526",
      "unix_kickoff": 1761767100,
      "category": "csv_index_empty"
    },
    {
      "event_id": "SErd2F3a",
      "dataset_label": "carabao_cup-2324",
      "unix_kickoff": 1691519400,
      "category": "csv_index_empty"
    },
    {
      "event_id": "QJNO78w3",
      "dataset_label": "carabao_cup-2223",
      "unix_kickoff": 1671565500,
      "category": "csv_index_empty"
    },
    {
      "event_id": "lnWSq0N7",
      "dataset_label": "carabao_cup-2526",
      "unix_kickoff": 1756233900,
      "category": "csv_index_empty"
    },
    {
      "event_id": "hzN85Q9l",
      "dataset_label": "fa_cup-2425",
      "unix_kickoff": 1739026800,
      "category": "csv_index_empty"
    },
    {
      "event_id": "xtphkLM7",
      "dataset_label": "ekstraklasa-2526",
      "unix_kickoff": 1765739700,
      "category": "no_ordered_hit_after_pmR",
      "diagnostic_wide_radius_days": 7
    },
    {
      "event_id": "ziOjypNM",
      "dataset_label": "fa_cup-2223",
      "unix_kickoff": 1675194300,
      "category": "csv_index_empty"
    },
    {
      "event_id": "GtzkusLq",
      "dataset_label": "carabao_cup-2223",
      "unix_kickoff": 1661280300,
      "category": "csv_index_empty"
    },
    {
      "event_id": "4OiJCF8c",
      "dataset_label": "fa_cup-2425",
      "unix_kickoff": 1730559600,
      "category": "csv_index_empty"
    },
    {
      "event_id": "xnPU8xrT",
      "dataset_label": "carabao_cup-2324",
      "unix_kickoff": 1691521200,
      "category": "csv_index_empty"
    },
    {
      "event_id": "AHz58q34",
      "dataset_label": "fa_cup-2526",
      "unix_kickoff": 1771156800,
      "category": "csv_index_empty"
    },
    {
      "event_id": "OY7Wt63i",
      "dataset_label": "fa_cup-2223",
      "unix_kickoff": 1667850300,
      "category": "csv_index_empty"
    },
    {
      "event_id": "KGZoK8uI",
      "dataset_label": "fa_cup-2324",
      "unix_kickoff": 1708976700,
      "category": "csv_index_empty"
    },
    {
      "event_id": "KU4yDIXR",
      "dataset_label": "fa_cup-2324",
      "unix_kickoff": 1710679500,
      "category": "csv_index_empty"
    },
    {
      "event_id": "d01ERQJr",
      "dataset_label": "carabao_cup-2526",
      "unix_kickoff": 1770235200,
      "category": "csv_index_empty"
    },
    {
      "event_id": "nRJm5SuI",
      "dataset_label": "ekstraklasa-2526",
      "unix_kickoff": 1776704400,
      "category": "no_ordered_hit_after_pmR",
      "diagnostic_wide_radius_days": 7
    },
    {
      "event_id": "tQbWscV8",
      "dataset_label": "fa_cup-2526",
      "unix_kickoff": 1762009200,
      "category": "csv_index_empty"
    },
    {
      "event_id": "0WtUENjg",
      "dataset_label": "ekstraklasa-2526",
      "unix_kickoff": 1773592200,
      "category": "no_ordered_hit_after_pmR",
      "diagnostic_wide_radius_days": 7
    },
    {
      "event_id": "2mDTXz66",
      "dataset_label": "fa_cup-2526",
      "unix_kickoff": 1768067100,
      "category": "csv_index_empty"
    },
    {
      "event_id": "MTHSnT8t",
      "dataset_label": "fa_cup-2223",
      "unix_kickoff": 1673186400,
      "category": "csv_index_empty"
    },
    {
      "event_id": "AyHiqYrL",
      "dataset_label": "carabao_cup-2324",
      "unix_kickoff": 1693335600,
      "category": "csv_index_empty"
    },
    {
      "event_id": "GEZ9Gs53",
      "dataset_label": "fa_cup-2223",
      "unix_kickoff": 1668541500,
      "category": "csv_index_empty"
    },
    {
      "event_id": "6XTbuIW1",
      "dataset_label": "carabao_cup-2526",
      "unix_kickoff": 1755024300,
      "category": "csv_index_empty"
    },
    {
      "event_id": "29QbwpuI",
      "dataset_label": "fa_cup-2324",
      "unix_kickoff": 1704553200,
      "category": "csv_index_empty"
    },
    {
      "event_id": "dnnL0h1e",
      "dataset_label": "fa_cup-2526",
      "unix_kickoff": 1771164000,
      "category": "csv_index_empty"
    },
    {
      "event_id": "p8tZ2bF5",
      "dataset_label": "fa_cup-2425",
      "unix_kickoff": 1732966200,
      "category": "csv_index_empty"
    },
    {
      "event_id": "Esk2zMam",
      "dataset_label": "ekstraklasa-2526",
      "unix_kickoff": 1765028700,
      "category": "no_ordered_hit_after_pmR",
      "diagnostic_wide_radius_days": 7
    },
    {
      "event_id": "Sh9BS8ig",
      "dataset_label": "carabao_cup-2425",
      "unix_kickoff": 1724784300,
      "category": "csv_index_empty"
    },
    {
      "event_id": "priBvrem",
      "dataset_label": "carabao_cup-2223",
      "unix_kickoff": 1660244400,
      "category": "csv_index_empty"
    }
  ],
  "lookup_miss_category_histogram_sample": {
    "csv_index_empty": 171,
    "no_ordered_hit_after_pmR": 29
  },
  "baseline_bottleneck_hint": "nigdy próby join: 5717/12141 (47.1%) — zakres CSV/unsupported; w scope join brak wpisu meta_ix: skipped_no_meta=5425; meta jest, brak dopasowania CSV: skipped_no_row~=982"
}
